korvus-1.1.5.dist-info/METADATA
korvus-1.1.5.dist-info/WHEEL
korvus/korvus.pyi
korvus/__init__.py
korvus/__main__.py
korvus/korvus.cpython-312-aarch64-linux-gnu.so
korvus-1.1.5.dist-info/RECORD
